Workbook

Sheet Como usar
A1: GUIA PRATICO MR-MPS-SW:2024 - DIAGNOSTICO E IMPLEMENTACAO ATE NIVEL C
A3: O que e este arquivo
A4: Instrumento de trabalho para (1) diagnosticar empiricamente em que nivel a unidade organizacional esta e (2) implementar, item a item, todos os resultados esperados (RE) cumulativos ate o nivel C.
A5: Base normativa: Guia Geral MPS de Software:2024 (SOFTEX). O texto de cada RE e literal do guia. As colunas 'Como checar', 'Evidencia', 'Como implementar', 'Erro comum' e 'Ferramenta' sao BOAS PRATICAS de mercado alinhadas ao RE - NAO sao regras oficiais da SOFTEX (o guia nao define como implementar; isso fica a cargo da organizacao).
A7: Abas do arquivo
A8: 1. Como usar - esta aba.
A9: 2. Diagnostico - a planilha principal. Uma linha por RE. Preencha Status, Evidencia encontrada, Responsavel, Prazo.
A10: 3. Painel - resumo automatico do percentual de implementacao por processo e por nivel.
A11: 4. Niveis de capacidade - o que cada CP exige (transversal a todos os processos).
A13: Como fazer o diagnostico empirico (passo a passo)
A14: Para CADA linha da aba Diagnostico:
A15: Passo 1 - Leia a coluna 'Como checar'. E uma pergunta de verificacao objetiva.
... A31: Itens com 'Requerido = Sim' tem exigencias textuais nao negociaveis no guia (ex: registro de riscos obrigatorio; HH nao e dimensao; definicao operacional de medida completa). Nesses, nao ha margem de interpretacao do avaliador.

Sheet Diagnostico
A1: # | B1: Grupo | C1: Processo | D1: Cod. Processo | E1: ID do RE | F1: Nivel | G1: Requerido | H1: Resultado Esperado (texto do guia) | I1: Como checar (verificacao) | J1: Evidencia esperada | K1: Como implementar (boa pratica) | L1: Erro comum | M1: Ferramenta sugerida | N1: STATUS | O1: Evidencia encontrada (link/onde) | P1: Responsavel | Q1: Prazo | R1: Observacoes
A2: 1 | B2: Projeto | C2: Gerencia de Projetos | D2: GPR | E2: GPR 1 | F2: G | G2: Nao | H2: O escopo do trabalho para o projeto e estabelecido, mantido atualizado e utilizado. | I2: Existe documento de escopo do projeto? Ele e atualizado quando ha mudancas? A equipe o usa para decidir o que esta dentro/fora? | J2: Documento de escopo / declaracao de escopo no plano de projeto, com historico de revisao. | K2: 1) Crie um campo/secao 'Escopo' no template de plano de projeto. 2) Liste o que esta incluido e o que esta excluido. 3) Vincule o escopo a um item de configuracao versionado. 4) Toda mudanca de escopo gera nova versao. | L2: Escopo escrito uma vez e nunca atualizado, ou misturado com requisitos sem fronteira clara. | M2: Jira (epics/descricao do projeto), Confluence, template de plano de projeto. | N2: P | O2: PRO-GPR-001 §4; TPL-GPR-002 (Termo de Abertura) / TPL-GPR-001 (Plano) | R2: Definicao/processo e template prontos no git; evidencia de execucao por projeto pendente (4 projetos da amostra nao selecionados).
A3: 2 | B3: Projeto | C3: Gerencia de Projetos | D3: GPR | E3: GPR 2 (ate E) | F3: G | G3: Sim | H3: O processo a ser utilizado para a execucao do projeto e descrito, mantido atualizado e utilizado. (Item requerido: nos niveis G e F a descricao do processo para o projeto deve conter, pelo menos, o ciclo de vida do projeto e a lista de tarefas que serao executadas.) | I3: O projeto tem o ciclo de vida descrito (fases) e a lista de tarefas? Esta documentado e e seguido? | J3: Descricao do ciclo de vida do projeto + lista de tarefas (WBS/quadro de tarefas). | K3: 1) Documente as fases do ciclo de vida (ex: analise, dev, teste, entrega). 2) Liste as tarefas tipicas de cada fase. 3) Registre isso no plano do projeto. 4) Garanta que o time siga essa sequencia. | L3: Confundir 'processo do projeto' com 'metodologia da empresa' sem registrar ciclo de vida e tarefas concretas. | M3: Jira (board com colunas=fases), Confluence. | N3: P | O3: PRO-GPC-001 (processo-padrao, 7 fases); TPL-GPR-003 (Adaptacao) | R3: Definicao/processo e template prontos no git; evidencia de execucao por projeto pendente (4 projetos da amostra nao selecionados).
A4: 3 | B4: Projeto | C4: Gerencia de Projetos | D4: GPR | E4: GPR 2+ (a partir de D) | F4: D | G4: Nao | H4: O processo definido para o projeto, derivado da estrategia para adaptacao do processo da organizacao, e estabelecido, mantido atualizado e utilizado. | I4: O processo do projeto foi DERIVADO do processo padrao organizacional aplicando as diretrizes de adaptacao (tailoring)? Ha registro dessa adaptacao? | J4: Registro de adaptacao (tailoring) do processo padrao para este projeto. | K4: 1) Tenha o processo padrao organizacional pronto (ver GPC). 2) Crie um formulario de adaptacao. 3) Para cada projeto, registre o que foi mantido/alterado/removido e por que. 4) Aprovacao do responsavel. | L4: Cada projeto inventa o proprio processo sem partir do padrao = falha de capacidade CP-E/D/C. | M4: Confluence (pagina de tailoring por projeto), template de adaptacao. | N4: P | O4: GUIA-GPC-001 (Guia de Adaptacao) + TPL-GPR-003 (Tailoring) | R4: Definicao/processo e template prontos no git; evidencia de execucao por projeto pendente (4 projetos da amostra nao selecionados).
A5: 4 | B5: Projeto | C5: Gerencia de Projetos | D5: GPR | E5: GPR 3 (ate E) | F5: G | G5: Sim | H5: Estimativas de dimensao da solucao sao estabelecidas e mantidas atualizadas. (Item requerido: HH nao pode ser considerada como dimensao.) | I5: Existe estimativa de TAMANHO da solucao (pontos de funcao, story points, etc.) - separada de esforco? HH NAO esta sendo usado como dimensao? | J5: Planilha/registro de estimativa de dimensao (PF, story points) com data. | K5: 1) Escolha uma metrica de dimensao (PF e a do edital CEMIG). 2) Estime a dimensao ANTES do esforco. 3) Registre o metodo. 4) Atualize quando o escopo mudar. NUNCA use horas como dimensao. | L5: Usar homem-hora como se fosse tamanho - explicitamente proibido pelo guia. | M5: Planilha de contagem de PF, ferramentas de APF, planning poker para story points. | N5: P | O5: PRO-GPR-001 §5 (dimensao em story points / planning poker) | R5: Definicao/processo e template prontos no git; evidencia de execucao por projeto pendente (4 projetos da amostra nao selecionados).
A6: 5 | B6: Projeto | C6: Gerencia de Projetos | D6: GPR | E6: GPR 3+ (a partir de D) | F6: D | G6: Nao | H6: Estimativas de dimensao da solucao sao estabelecidas com a utilizacao de metodos apropriados e documentados, e sao mantidas atualizadas. | I6: O metodo de estimativa de dimensao esta documentado e padronizado na organizacao (nao improvisado por projeto)? | J6: Procedimento documentado de estimativa de dimensao + aplicacao registrada. | K6: 1) Documente o metodo (ex: roteiro de contagem de PF da CEMIG). 2) Treine a equipe. 3) Aplique consistentemente. 4) Versione o procedimento. | L6: Metodo na cabeca de uma pessoa, sem documentacao reaproveitavel. | M6: Roteiro de metricas, Confluence. | N6: P | O6: PRO-GPR-001 §5 (metodo de estimativa documentado) | R6: Definicao/processo e template prontos no git; evidencia de execucao por projeto pendente (4 projetos da amostra nao selecionados).
A7: 6 | B7: Projeto | C7: Gerencia de Projetos | D7: GPR | E7: GPR 4 (ate E) | F7: G | G7: Sim | H7: Estimativas de esforco, duracao e custo para a execucao das tarefas e dos produtos de trabalho do projeto sao estabelecidas e justificadas. (Item requerido: devem ser derivadas das estimativas de dimensao; a justificativa deve conter um racional de como foram realizadas.) | I7: As estimativas de esforco/prazo/custo derivam da dimensao (GPR 3)? Ha justificativa registrada de COMO foram feitas? | J7: Planilha de estimativas com racional documentado, partindo da dimensao. | K7: 1) Parta da dimensao (PF). 2) Use indice de produtividade (HH por PF) para chegar ao esforco. 3) Derive prazo e custo. 4) Escreva o racional ('X PF * Y HH/PF = Z HH'). | L7: Estimar esforco 'no chute' sem ligacao com a dimensao, ou sem registrar o racional. | M7: Planilha de estimativas, dados historicos de produtividade. | N7: P | O7: PRO-GPR-001 §5 (esforco/prazo/custo a partir do tamanho) | R7: Definicao/processo e template prontos no git; evidencia de execucao por projeto pendente (4 projetos da amostra nao selecionados).
A8: 7 | B8: Projeto | C8: Gerencia de Projetos | D8: GPR | E8: GPR 4+ (a partir de D) | F8: D | G8: Sim | H8: Estimativas de esforco, duracao e custo sao estabelecidas e justificadas utilizando metodos apropriados, baseadas no repositorio organizacional de medidas e no conjunto de ativos de processo organizacional. (Item requerido: derivadas das estimativas de dimensao.) | I8: As estimativas usam dados do REPOSITORIO ORGANIZACIONAL de medidas (historico de varios projetos), nao so do projeto atual? | J8: Estimativa referenciando o repositorio organizacional de medidas. | K8: 1) Construa o repositorio organizacional de medidas (ver GPC 9). 2) Calcule produtividade media historica. 3) Baseie novas estimativas nesses dados. 4) Registre a fonte. | L8: Ter repositorio mas nao usar nas estimativas; ou nao ter historico consolidado. | M8: Repositorio organizacional de medidas (planilha/BD), Power BI. | N8: P | O8: PRO-GPR-001 §5 + PLA-MED-001 (velocity/dados historicos = repositorio) | R8: Definicao/processo e template prontos no git; evidencia de execucao por projeto pendente (4 projetos da amostra nao selecionados).
A9: 8 | B9: Projeto | C9: Gerencia de Projetos | D9: GPR | E9: GPR 5 | F9: G | G9: Nao | H9: O orcamento e o cronograma do projeto, incluindo a definicao de marcos, sao estabelecidos e mantidos atualizados. | I9: Existe cronograma com marcos e orcamento? Sao atualizados ao longo do projeto? | J9: Cronograma com marcos + orcamento, com versoes. | K9: 1) Monte cronograma com marcos visiveis. 2) Associe orcamento. 3) Atualize a cada replanejamento. 4) Versione. | L9: Cronograma feito no inicio e nunca mais tocado. | M9: MS Project, Jira (roadmap), planilha de cronograma. | N9: P | O9: TPL-GPR-001 (cronograma/orcamento) + Jira | R9: Definicao/processo e template prontos no git; evidencia de execucao por projeto pendente (4 projetos da amostra nao selecionados).
A10: 9 | B10: Projeto | C10: Gerencia de Projetos | D10: GPR | E10: GPR 6 | F10: G | G10: Nao | H10: Os recursos humanos para o projeto sao planejados considerando as habilidades e os conhecimentos necessarios para executa-lo. | I10: Ha planejamento de quem trabalha no projeto, considerando habilidades necessarias? | J10: Plano de alocacao de pessoas com perfil/habilidade requerida. | K10: 1) Liste as habilidades que o projeto exige. 2) Mapeie quem tem. 3) Registre a alocacao. 4) Se faltar habilidade, planeje treinamento/contratacao (liga com CAP). | L10: Alocar pessoas por disponibilidade sem olhar competencia. | M10: Matriz de competencias, plano de projeto. | N10: P | O10: TPL-GPR-001 (plano de recursos humanos) | R10: Definicao/processo e template prontos no git; evidencia de execucao por projeto pendente (4 projetos da amostra nao selecionados).
A11: 10 | B11: Projeto | C11: Gerencia de Projetos | D11: GPR | E11: GPR 7 (ate E) | F11: G | G11: Nao | H11: Os recursos materiais e o ambiente de trabalho necessarios para executar o projeto sao estabelecidos e mantidos atualizados. | I11: Estao definidos os recursos materiais e o ambiente (hardware, software, licencas, ambientes de dev/teste)? | J11: Lista de recursos materiais e ambiente no plano de projeto. | K11: 1) Liste ambientes (dev, homolog, prod), ferramentas e licencas. 2) Garanta provisionamento. 3) Atualize quando mudar. | L11: Descobrir no meio do projeto que falta ambiente/licenca. | M11: Plano de projeto, inventario de TI. | N11: P | O11: TPL-GPR-001 (recursos materiais/ambiente) | R11: Definicao/processo e template prontos no git; evidencia de execucao por projeto pendente (4 projetos da amostra nao selecionados).
A12: 11 | B12: Projeto | C12: Gerencia de Projetos | D12: GPR | E12: GPR 7+ (a partir de D) | F12: D | G12: Nao | H12: Os recursos materiais e o ambiente de trabalho sao estabelecidos a partir dos ambientes padrao de trabalho da organizacao, e sao mantidos atualizados. | I12: Os ambientes do projeto derivam dos AMBIENTES PADRAO da organizacao (GPC 8)? | J12: Referencia ao ambiente padrao organizacional na configuracao do projeto. | K12: 1) Defina ambientes padrao na organizacao (ver GPC 8). 2) Projetos partem deles. 3) Registre adaptacoes. | L12: Cada projeto monta ambiente do zero, sem padrao. | M12: IaC (Terraform), imagens padrao, Confluence. | N12: P | O12: PLA-GPC-001 §3 (ambientes-padrao) referenciado no plano | R12: Definicao/processo e template prontos no git; evidencia de execucao por projeto pendente (4 projetos da amostra nao selecionados).
A13: 12 | B13: Projeto | C13: Gerencia de Projetos | D13: GPR | E13: GPR 8 | F13: G | G13: Nao | H13: A estrategia de transicao para operacao e suporte do produto, incluindo as tarefas e o cronograma, e planejada. | I13: Existe plano de como o produto entra em operacao/suporte (handover, tarefas, prazos)? | J13: Plano de transicao para operacao/suporte. | K13: 1) Defina como o produto vai para producao e quem assume o suporte. 2) Liste tarefas de transicao. 3) Coloque no cronograma. | L13: Entregar sem plano de sustentacao - critico no contexto CEMIG (AMS). | M13: Plano de transicao, runbook. | N13: P | O13: PRO-GPR-001 §6 / TPL-GPR-001 (transicao p/ operacao) | R13: Definicao/processo e template prontos no git; evidencia de execucao por projeto pendente (4 projetos da amostra nao selecionados).
... A117: 116 | B117: Organizacional | C117: Gerencia Organizacional de Software | D117: OSW | E117: OSW 10 (a partir de C) | F117: C | G117: Nao | H117: Os projetos do portfolio que atendem aos acordos e requisitos que levaram a sua aprovacao sao mantidos, e os que nao atendem sao tratados conforme pertinente, considerando o acordo estabelecido. (Excluivel se projeto unico.) | I117: Os projetos do portfolio sao acompanhados contra o que justificou sua aprovacao, com tratamento dos que desviam? (Excluivel se projeto unico.) | J117: Registro de acompanhamento e tratamento de projetos do portfolio. | K117: 1) Acompanhe se cada projeto ainda atende ao que justificou aprova-lo. 2) Trate (continuar/ajustar/cancelar). 3) Registre. | L117: Manter projeto que ja nao faz sentido no portfolio. | M117: Revisao de portfolio (stage-gate). | N117: P | O117: PRO-OSW-002 §5 (acompanhamento/tratamento de projetos do portfolio) | R117: Processo definido; registros de acompanhamento do portfolio pendentes (nivel C).

Sheet Painel
A1: PAINEL DE PROGRESSO
A2: Atualiza automaticamente conforme a coluna STATUS da aba Diagnostico e preenchida. % Implementado considera T e L como implementados; ignora NA.
A4: Processo | B4: Cod | C4: Total RE | D4: T | E4: L | F4: P | G4: N | H4: NA | I4: % Implementado (T+L)
A5: Gerencia de Projetos | B5: GPR | C5: =COUNTIF(Diagnostico!$D$2:$D$117,B5) | D5: =COUNTIFS(Diagnostico!$D$2:$D$117,B5,Diagnostico!$N$2:$N$117,"T") | E5: =COUNTIFS(Diagnostico!$D$2:$D$117,B5,Diagnostico!$N$2:$N$117,"L") | F5: =COUNTIFS(Diagnostico!$D$2:$D$117,B5,Diagnostico!$N$2:$N$117,"P") | G5: =COUNTIFS(Diagnostico!$D$2:$D$117,B5,Diagnostico!$N$2:$N$117,"N") | H5: =COUNTIFS(Diagnostico!$D$2:$D$117,B5,Diagnostico!$N$2:$N$117,"NA") | I5: =IFERROR((D5+E5)/(C5-H5),0)
A6: Engenharia de Requisitos | B6: REQ | C6: =COUNTIF(Diagnostico!$D$2:$D$117,B6) | D6: =COUNTIFS(Diagnostico!$D$2:$D$117,B6,Diagnostico!$N$2:$N$117,"T") | E6: =COUNTIFS(Diagnostico!$D$2:$D$117,B6,Diagnostico!$N$2:$N$117,"L") | F6: =COUNTIFS(Diagnostico!$D$2:$D$117,B6,Diagnostico!$N$2:$N$117,"P") | G6: =COUNTIFS(Diagnostico!$D$2:$D$117,B6,Diagnostico!$N$2:$N$117,"N") | H6: =COUNTIFS(Diagnostico!$D$2:$D$117,B6,Diagnostico!$N$2:$N$117,"NA") | I6: =IFERROR((D6+E6)/(C6-H6),0)
A7: Projeto e Construcao do Produto | B7: PCP | C7: =COUNTIF(Diagnostico!$D$2:$D$117,B7) | D7: =COUNTIFS(Diagnostico!$D$2:$D$117,B7,Diagnostico!$N$2:$N$117,"T") | E7: =COUNTIFS(Diagnostico!$D$2:$D$117,B7,Diagnostico!$N$2:$N$117,"L") | F7: =COUNTIFS(Diagnostico!$D$2:$D$117,B7,Diagnostico!$N$2:$N$117,"P") | G7: =COUNTIFS(Diagnostico!$D$2:$D$117,B7,Diagnostico!$N$2:$N$117,"N") | H7: =COUNTIFS(Diagnostico!$D$2:$D$117,B7,Diagnostico!$N$2:$N$117,"NA") | I7: =IFERROR((D7+E7)/(C7-H7),0)
A8: Integracao do Produto | B8: ITP | C8: =COUNTIF(Diagnostico!$D$2:$D$117,B8) | D8: =COUNTIFS(Diagnostico!$D$2:$D$117,B8,Diagnostico!$N$2:$N$117,"T") | E8: =COUNTIFS(Diagnostico!$D$2:$D$117,B8,Diagnostico!$N$2:$N$117,"L") | F8: =COUNTIFS(Diagnostico!$D$2:$D$117,B8,Diagnostico!$N$2:$N$117,"P") | G8: =COUNTIFS(Diagnostico!$D$2:$D$117,B8,Diagnostico!$N$2:$N$117,"N") | H8: =COUNTIFS(Diagnostico!$D$2:$D$117,B8,Diagnostico!$N$2:$N$117,"NA") | I8: =IFERROR((D8+E8)/(C8-H8),0)
A9: Verificacao e Validacao | B9: VV | C9: =COUNTIF(Diagnostico!$D$2:$D$117,B9) | D9: =COUNTIFS(Diagnostico!$D$2:$D$117,B9,Diagnostico!$N$2:$N$117,"T") | E9: =COUNTIFS(Diagnostico!$D$2:$D$117,B9,Diagnostico!$N$2:$N$117,"L") | F9: =COUNTIFS(Diagnostico!$D$2:$D$117,B9,Diagnostico!$N$2:$N$117,"P") | G9: =COUNTIFS(Diagnostico!$D$2:$D$117,B9,Diagnostico!$N$2:$N$117,"N") | H9: =COUNTIFS(Diagnostico!$D$2:$D$117,B9,Diagnostico!$N$2:$N$117,"NA") | I9: =IFERROR((D9+E9)/(C9-H9),0)
A10: Gerencia de Configuracao | B10: GCO | C10: =COUNTIF(Diagnostico!$D$2:$D$117,B10) | D10: =COUNTIFS(Diagnostico!$D$2:$D$117,B10,Diagnostico!$N$2:$N$117,"T") | E10: =COUNTIFS(Diagnostico!$D$2:$D$117,B10,Diagnostico!$N$2:$N$117,"L") | F10: =COUNTIFS(Diagnostico!$D$2:$D$117,B10,Diagnostico!$N$2:$N$117,"P") | G10: =COUNTIFS(Diagnostico!$D$2:$D$117,B10,Diagnostico!$N$2:$N$117,"N") | H10: =COUNTIFS(Diagnostico!$D$2:$D$117,B10,Diagnostico!$N$2:$N$117,"NA") | I10: =IFERROR((D10+E10)/(C10-H10),0)
A11: Aquisicao | B11: AQU | C11: =COUNTIF(Diagnostico!$D$2:$D$117,B11) | D11: =COUNTIFS(Diagnostico!$D$2:$D$117,B11,Diagnostico!$N$2:$N$117,"T") | E11: =COUNTIFS(Diagnostico!$D$2:$D$117,B11,Diagnostico!$N$2:$N$117,"L") | F11: =COUNTIFS(Diagnostico!$D$2:$D$117,B11,Diagnostico!$N$2:$N$117,"P") | G11: =COUNTIFS(Diagnostico!$D$2:$D$117,B11,Diagnostico!$N$2:$N$117,"N") | H11: =COUNTIFS(Diagnostico!$D$2:$D$117,B11,Diagnostico!$N$2:$N$117,"NA") | I11: =IFERROR((D11+E11)/(C11-H11),0)
A12: Medicao | B12: MED | C12: =COUNTIF(Diagnostico!$D$2:$D$117,B12) | D12: =COUNTIFS(Diagnostico!$D$2:$D$117,B12,Diagnostico!$N$2:$N$117,"T") | E12: =COUNTIFS(Diagnostico!$D$2:$D$117,B12,Diagnostico!$N$2:$N$117,"L") | F12: =COUNTIFS(Diagnostico!$D$2:$D$117,B12,Diagnostico!$N$2:$N$117,"P") | G12: =COUNTIFS(Diagnostico!$D$2:$D$117,B12,Diagnostico!$N$2:$N$117,"N") | H12: =COUNTIFS(Diagnostico!$D$2:$D$117,B12,Diagnostico!$N$2:$N$117,"NA") | I12: =IFERROR((D12+E12)/(C12-H12),0)
A13: Gerencia de Decisoes | B13: GDE | C13: =COUNTIF(Diagnostico!$D$2:$D$117,B13) | D13: =COUNTIFS(Diagnostico!$D$2:$D$117,B13,Diagnostico!$N$2:$N$117,"T") | E13: =COUNTIFS(Diagnostico!$D$2:$D$117,B13,Diagnostico!$N$2:$N$117,"L") | F13: =COUNTIFS(Diagnostico!$D$2:$D$117,B13,Diagnostico!$N$2:$N$117,"P") | G13: =COUNTIFS(Diagnostico!$D$2:$D$117,B13,Diagnostico!$N$2:$N$117,"N") | H13: =COUNTIFS(Diagnostico!$D$2:$D$117,B13,Diagnostico!$N$2:$N$117,"NA") | I13: =IFERROR((D13+E13)/(C13-H13),0)
A14: Capacitacao | B14: CAP | C14: =COUNTIF(Diagnostico!$D$2:$D$117,B14) | D14: =COUNTIFS(Diagnostico!$D$2:$D$117,B14,Diagnostico!$N$2:$N$117,"T") | E14: =COUNTIFS(Diagnostico!$D$2:$D$117,B14,Diagnostico!$N$2:$N$117,"L") | F14: =COUNTIFS(Diagnostico!$D$2:$D$117,B14,Diagnostico!$N$2:$N$117,"P") | G14: =COUNTIFS(Diagnostico!$D$2:$D$117,B14,Diagnostico!$N$2:$N$117,"N") | H14: =COUNTIFS(Diagnostico!$D$2:$D$117,B14,Diagnostico!$N$2:$N$117,"NA") | I14: =IFERROR((D14+E14)/(C14-H14),0)
A15: Gerencia de Processos | B15: GPC | C15: =COUNTIF(Diagnostico!$D$2:$D$117,B15) | D15: =COUNTIFS(Diagnostico!$D$2:$D$117,B15,Diagnostico!$N$2:$N$117,"T") | E15: =COUNTIFS(Diagnostico!$D$2:$D$117,B15,Diagnostico!$N$2:$N$117,"L") | F15: =COUNTIFS(Diagnostico!$D$2:$D$117,B15,Diagnostico!$N$2:$N$117,"P") | G15: =COUNTIFS(Diagnostico!$D$2:$D$117,B15,Diagnostico!$N$2:$N$117,"N") | H15: =COUNTIFS(Diagnostico!$D$2:$D$117,B15,Diagnostico!$N$2:$N$117,"NA") | I15: =IFERROR((D15+E15)/(C15-H15),0)
A16: Gerencia Organizacional de Software | B16: OSW | C16: =COUNTIF(Diagnostico!$D$2:$D$117,B16) | D16: =COUNTIFS(Diagnostico!$D$2:$D$117,B16,Diagnostico!$N$2:$N$117,"T") | E16: =COUNTIFS(Diagnostico!$D$2:$D$117,B16,Diagnostico!$N$2:$N$117,"L") | F16: =COUNTIFS(Diagnostico!$D$2:$D$117,B16,Diagnostico!$N$2:$N$117,"P") | G16: =COUNTIFS(Diagnostico!$D$2:$D$117,B16,Diagnostico!$N$2:$N$117,"N") | H16: =COUNTIFS(Diagnostico!$D$2:$D$117,B16,Diagnostico!$N$2:$N$117,"NA") | I16: =IFERROR((D16+E16)/(C16-H16),0)
A17: TOTAL GERAL | C17: =SUM(C5:C16) | D17: =SUM(D5:D16) | E17: =SUM(E5:E16) | F17: =SUM(F5:F16) | G17: =SUM(G5:G16) | H17: =SUM(H5:H16) | I17: =IFERROR((D17+E17)/(C17-H17),0)
A19: PROGRESSO POR NIVEL (cumulativo)
A20: Nivel | B20: Total RE | C20: T | D20: L | E20: P | F20: N | G20: NA | H20: % Implementado
A21: G - Parc. Gerenciado | B21: =COUNTIF(Diagnostico!$F$2:$F$117,"G") | C21: =COUNTIFS(Diagnostico!$F$2:$F$117,"G",Diagnostico!$N$2:$N$117,"T") | D21: =COUNTIFS(Diagnostico!$F$2:$F$117,"G",Diagnostico!$N$2:$N$117,"L") | E21: =COUNTIFS(Diagnostico!$F$2:$F$117,"G",Diagnostico!$N$2:$N$117,"P") | F21: =COUNTIFS(Diagnostico!$F$2:$F$117,"G",Diagnostico!$N$2:$N$117,"N") | G21: =COUNTIFS(Diagnostico!$F$2:$F$117,"G",Diagnostico!$N$2:$N$117,"NA") | H21: =IFERROR((C21+D21)/(B21-G21),0)
A22: F - Gerenciado | B22: =COUNTIF(Diagnostico!$F$2:$F$117,"F") | C22: =COUNTIFS(Diagnostico!$F$2:$F$117,"F",Diagnostico!$N$2:$N$117,"T") | D22: =COUNTIFS(Diagnostico!$F$2:$F$117,"F",Diagnostico!$N$2:$N$117,"L") | E22: =COUNTIFS(Diagnostico!$F$2:$F$117,"F",Diagnostico!$N$2:$N$117,"P") | F22: =COUNTIFS(Diagnostico!$F$2:$F$117,"F",Diagnostico!$N$2:$N$117,"N") | G22: =COUNTIFS(Diagnostico!$F$2:$F$117,"F",Diagnostico!$N$2:$N$117,"NA") | H22: =IFERROR((C22+D22)/(B22-G22),0)
A23: E - Parc. Definido | B23: =COUNTIF(Diagnostico!$F$2:$F$117,"E") | C23: =COUNTIFS(Diagnostico!$F$2:$F$117,"E",Diagnostico!$N$2:$N$117,"T") | D23: =COUNTIFS(Diagnostico!$F$2:$F$117,"E",Diagnostico!$N$2:$N$117,"L") | E23: =COUNTIFS(Diagnostico!$F$2:$F$117,"E",Diagnostico!$N$2:$N$117,"P") | F23: =COUNTIFS(Diagnostico!$F$2:$F$117,"E",Diagnostico!$N$2:$N$117,"N") | G23: =COUNTIFS(Diagnostico!$F$2:$F$117,"E",Diagnostico!$N$2:$N$117,"NA") | H23: =IFERROR((C23+D23)/(B23-G23),0)
A24: D - Largamente Definido | B24: =COUNTIF(Diagnostico!$F$2:$F$117,"D") | C24: =COUNTIFS(Diagnostico!$F$2:$F$117,"D",Diagnostico!$N$2:$N$117,"T") | D24: =COUNTIFS(Diagnostico!$F$2:$F$117,"D",Diagnostico!$N$2:$N$117,"L") | E24: =COUNTIFS(Diagnostico!$F$2:$F$117,"D",Diagnostico!$N$2:$N$117,"P") | F24: =COUNTIFS(Diagnostico!$F$2:$F$117,"D",Diagnostico!$N$2:$N$117,"N") | G24: =COUNTIFS(Diagnostico!$F$2:$F$117,"D",Diagnostico!$N$2:$N$117,"NA") | H24: =IFERROR((C24+D24)/(B24-G24),0)
A25: C - Definido | B25: =COUNTIF(Diagnostico!$F$2:$F$117,"C") | C25: =COUNTIFS(Diagnostico!$F$2:$F$117,"C",Diagnostico!$N$2:$N$117,"T") | D25: =COUNTIFS(Diagnostico!$F$2:$F$117,"C",Diagnostico!$N$2:$N$117,"L") | E25: =COUNTIFS(Diagnostico!$F$2:$F$117,"C",Diagnostico!$N$2:$N$117,"P") | F25: =COUNTIFS(Diagnostico!$F$2:$F$117,"C",Diagnostico!$N$2:$N$117,"N") | G25: =COUNTIFS(Diagnostico!$F$2:$F$117,"C",Diagnostico!$N$2:$N$117,"NA") | H25: =IFERROR((C25+D25)/(B25-G25),0)

Sheet Niveis de capacidade
A1: NIVEIS DE CAPACIDADE DO PROCESSO (CP) - MR-MPS-SW:2024
A2: A capacidade descreve COMO o processo e executado (transversal a TODOS os processos do nivel). Alem dos resultados esperados de cada processo, a unidade precisa atender ao nivel de capacidade correspondente. Texto resumido do guia 2024.
A4: Nivel | B4: O que a capacidade exige
A5: G | B5: CP-G: A execucao do processo e gerenciada (produz resultados, e planejada e monitorada, pessoas preparadas).
A6: F | B6: CP-F: Execucao e produtos de trabalho gerenciados (+ verificacao objetiva de aderencia + avaliacao objetiva de produtos + tratamento de nao conformidades).
A7: E | B7: CP-E/D/C: O processo e definido (+ processo padrao e diretrizes de adaptacao usados; verificacao de aderencia E efetividade; oportunidades de melhoria identificadas na GQ; ativos de processo disponibilizados).
A8: D | B8: CP-E/D/C: O processo e definido (mesmos resultados de capacidade do nivel E aplicados aos processos que evoluem em D).
A9: C | B9: CP-E/D/C: O processo e definido (mesmos resultados de capacidade; foco organizacional consolidado).
